dash_pivottable/PivotTable.py
dash_pivottable/__init__.py
dash_pivottable/_imports_.py
dash_pivottable/dash_pivottable.dev.js
dash_pivottable/dash_pivottable.min.js
dash_pivottable/metadata.json
dash_pivottable/package.json
datrics_dash_pivottable-0.0.2.1.dist-info/LICENSE
datrics_dash_pivottable-0.0.2.1.dist-info/METADATA
datrics_dash_pivottable-0.0.2.1.dist-info/WHEEL
datrics_dash_pivottable-0.0.2.1.dist-info/top_level.txt
datrics_dash_pivottable-0.0.2.1.dist-info/RECORD
