Metadata-Version: 2.1
Name: datrics-dash-pivottable
Version: 0.0.2.1
Summary: Fixed version of the dash_pivottable=0.0.2
Author: Roman Malkevych
Author-email: rm@datrics.ai
License: MIT
License-File: LICENSE
Requires-Dist: dash
